trendalation/__init__.py
trendalation/classification.py
trendalation/metrics.py
trendalation/version.py
trendalation-1.0.2.dist-info/LICENSE.rst
trendalation-1.0.2.dist-info/METADATA
trendalation-1.0.2.dist-info/WHEEL
trendalation-1.0.2.dist-info/top_level.txt
trendalation-1.0.2.dist-info/RECORD
