Metadata-Version: 2.1
Name: trendalation
Version: 1.0.2
Home-page: https://github.com/kartikeysinha/trendalation
Author: ['Raghav Saboo', 'Kartikey Sinha']
Author-email: raghs2000@gmail.com
License: MIT
Keywords: anomaly detection,time-series,procrustes,trends,spatial analysis
Classifier: Development Status :: 3 - Alpha
Classifier: Intended Audience :: Developers
Classifier: Topic :: Software Development :: Build Tools
Classifier: License :: OSI Approved :: MIT License
Classifier: Programming Language :: Python :: 3.8
Requires-Python: >=3.8
License-File: LICENSE.rst
Requires-Dist: numpy
Requires-Dist: scikit-learn
Requires-Dist: scipy
Requires-Dist: pytest
